pytest_conductor/__init__.py
pytest_conductor/core.py
pytest_conductor/hooks.py
pytest_conductor-0.2.0.dist-info/METADATA
pytest_conductor-0.2.0.dist-info/WHEEL
pytest_conductor-0.2.0.dist-info/entry_points.txt
pytest_conductor-0.2.0.dist-info/licenses/LICENSE
pytest_conductor-0.2.0.dist-info/RECORD
