Metadata-Version: 2.4
Name: pytest-conductor
Version: 0.2.0
Summary: Pytest plugin for coordinating the order in which marked tests run.
Author-email: Samuel Chai <samuel.chai.development@gmail.com>
License-File: LICENSE
Requires-Python: >=3.8
Requires-Dist: pytest<8.4; python_version == '3.8'
Requires-Dist: pytest<9.0; python_version > '3.8'
